energy_dependency_inspector/__init__.py
energy_dependency_inspector/__main__.py
energy_dependency_inspector/core/__init__.py
energy_dependency_inspector/core/interfaces.py
energy_dependency_inspector/core/orchestrator.py
energy_dependency_inspector/core/output_formatter.py
energy_dependency_inspector/core/venv_checker.py
energy_dependency_inspector/detectors/__init__.py
energy_dependency_inspector/detectors/apk_detector.py
energy_dependency_inspector/detectors/docker_info_detector.py
energy_dependency_inspector/detectors/dpkg_detector.py
energy_dependency_inspector/detectors/maven_detector.py
energy_dependency_inspector/detectors/npm_detector.py
energy_dependency_inspector/detectors/pip_detector.py
energy_dependency_inspector/executors/__init__.py
energy_dependency_inspector/executors/docker_executor.py
energy_dependency_inspector/executors/host_executor.py
energy_dependency_inspector-0.2.1.dist-info/licenses/LICENSE
energy_dependency_inspector-0.2.1.dist-info/METADATA
energy_dependency_inspector-0.2.1.dist-info/WHEEL
energy_dependency_inspector-0.2.1.dist-info/entry_points.txt
energy_dependency_inspector-0.2.1.dist-info/top_level.txt
energy_dependency_inspector-0.2.1.dist-info/RECORD
