Metadata-Version: 2.4
Name: energy-dependency-inspector
Version: 0.2.1
Summary: Captures dependency snapshots of software systems for tracking changes across measurements. Originally designed for energy measurement contexts, also usable as a general-purpose dependency resolver.
Author: David Kopp, Arne Tarara
License: MIT
Project-URL: Repository, https://github.com/green-coding-solutions/energy-dependency-inspector
Keywords: dependencies,docker,containers,package-manager,energy,inspection,snapshot,resolver
Classifier: Development Status :: 4 - Beta
Classifier: Intended Audience :: Developers
Classifier: Intended Audience :: System Administrators
Classifier: Topic :: Software Development :: Libraries :: Python Modules
Classifier: Topic :: System :: Systems Administration
Classifier: Topic :: System :: Monitoring
Classifier: Topic :: Utilities
Classifier: Programming Language :: Python :: 3
Classifier: Programming Language :: Python :: 3.10
Classifier: Programming Language :: Python :: 3.11
Classifier: Programming Language :: Python :: 3.12
Classifier: License :: OSI Approved :: MIT License
Requires-Python: >=3.10
License-File: LICENSE
Requires-Dist: docker>=6.0.0
Provides-Extra: dev
Requires-Dist: pytest>=7.0.0; extra == "dev"
Requires-Dist: pytest-cov>=4.0.0; extra == "dev"
Requires-Dist: pylint>=2.15.0; extra == "dev"
Requires-Dist: mypy>=1.0.0; extra == "dev"
Requires-Dist: types-docker; extra == "dev"
Requires-Dist: black>=22.0.0; extra == "dev"
Requires-Dist: pre-commit>=3.0.0; extra == "dev"
Dynamic: license-file
